rituals/__init__.py
rituals/config.py
rituals/easy.py
rituals/acts/__init__.py
rituals/acts/basic.py
rituals/acts/devpi.py
rituals/acts/documentation.py
rituals/acts/github.py
rituals/acts/inspection.py
rituals/acts/jenkins.py
rituals/acts/pkgdeb.py
rituals/acts/releasing.py
rituals/acts/testing.py
rituals/util/__init__.py
rituals/util/_compat.py
rituals/util/antglob.py
rituals/util/buildsys.py
rituals/util/filesys.py
rituals/util/notify.py
rituals/util/shell.py
rituals/util/which.py
rituals/util/scm/__init__.py
rituals/util/scm/base.py
rituals/util/scm/git.py
rituals/util/scm/null.py
rituals-0.4.2.data/data/EGG-INFO/LICENSE
rituals-0.4.2.data/data/EGG-INFO/README.md
rituals-0.4.2.data/data/EGG-INFO/changelog
rituals-0.4.2.dist-info/LICENSE
rituals-0.4.2.dist-info/METADATA
rituals-0.4.2.dist-info/WHEEL
rituals-0.4.2.dist-info/entry_points.txt
rituals-0.4.2.dist-info/top_level.txt
rituals-0.4.2.dist-info/RECORD
