Metadata-Version: 2.1
Name: rituals
Version: 0.4.2
Summary: Common tasks for 'Invoke' that are needed again and again.
Home-page: https://github.com/jhermann/rituals
Author: Jürgen Hermann
Author-email: jh@web.de
License: GPL v2
Keywords: invoke,automation,tasks,release,deploy,distribute,publish
Platform: UNKNOWN
Classifier: Development Status :: 5 - Production/Stable
Classifier: Environment :: Console
Classifier: Intended Audience :: Developers
Classifier: License :: OSI Approved :: GNU General Public License v2 (GPLv2)
Classifier: Operating System :: OS Independent
Classifier: Programming Language :: Python :: 3.6
Classifier: Programming Language :: Python :: 3.7
Classifier: Programming Language :: Python :: 3.8
Classifier: Programming Language :: Python :: 3.9
Classifier: Topic :: Software Development
Classifier: Topic :: Software Development :: Build Tools
Classifier: Topic :: Utilities
Requires-Dist: munch (<3,>2)
Requires-Dist: invoke (>=1.5)
Requires-Dist: toml (>=0.10.1)
Requires-Dist: requests (>=2.9)
Requires-Dist: pathlib2 ; python_version == "2.7"
